fz_manager/__init__.py
fz_manager/factorio_zone_api.py
fz_manager/main.py
fz_manager/menu.py
fz_manager/shell.py
fz_manager/storage.py
fz_manager/titlebar.py
fz_manager/utils.py
fz_manager-0.1.1.dist-info/entry_points.txt
fz_manager-0.1.1.dist-info/LICENSE
fz_manager-0.1.1.dist-info/WHEEL
fz_manager-0.1.1.dist-info/METADATA
fz_manager-0.1.1.dist-info/RECORD
